binning/__init__.py
binning/_binning.py
binning/_version.py
daa_adaptive_binning-0.0.3.dist-info/LICENSE
daa_adaptive_binning-0.0.3.dist-info/METADATA
daa_adaptive_binning-0.0.3.dist-info/WHEEL
daa_adaptive_binning-0.0.3.dist-info/top_level.txt
daa_adaptive_binning-0.0.3.dist-info/RECORD
